westpa/__init__.py
westpa/_version.py
westpa/analysis/__init__.py
westpa/analysis/core.py
westpa/analysis/statistics.py
westpa/analysis/trajectories.py
westpa/cli/__init__.py
westpa/cli/core/__init__.py
westpa/cli/core/w_fork.py
westpa/cli/core/w_init.py
westpa/cli/core/w_run.py
westpa/cli/core/w_states.py
westpa/cli/core/w_succ.py
westpa/cli/core/w_truncate.py
westpa/cli/tools/__init__.py
westpa/cli/tools/ploterr.py
westpa/cli/tools/plothist.py
westpa/cli/tools/w_assign.py
westpa/cli/tools/w_bins.py
westpa/cli/tools/w_crawl.py
westpa/cli/tools/w_direct.py
westpa/cli/tools/w_dumpsegs.py
westpa/cli/tools/w_eddist.py
westpa/cli/tools/w_fluxanl.py
westpa/cli/tools/w_ipa.py
westpa/cli/tools/w_kinavg.py
westpa/cli/tools/w_kinetics.py
westpa/cli/tools/w_multi_west.py
westpa/cli/tools/w_ntop.py
westpa/cli/tools/w_pdist.py
westpa/cli/tools/w_postanalysis_matrix.py
westpa/cli/tools/w_postanalysis_reweight.py
westpa/cli/tools/w_red.py
westpa/cli/tools/w_reweight.py
westpa/cli/tools/w_select.py
westpa/cli/tools/w_stateprobs.py
westpa/cli/tools/w_timings.py
westpa/cli/tools/w_trace.py
westpa/core/__init__.py
westpa/core/_rc.py
westpa/core/data_manager.py
westpa/core/extloader.py
westpa/core/h5io.py
westpa/core/progress.py
westpa/core/segment.py
westpa/core/sim_manager.py
westpa/core/states.py
westpa/core/systems.py
westpa/core/textio.py
westpa/core/trajectory.py
westpa/core/we_driver.py
westpa/core/wm_ops.py
westpa/core/yamlcfg.py
westpa/core/binning/__init__.py
westpa/core/binning/_assign.c
westpa/core/binning/_assign.cpython-314-aarch64-linux-gnu.so
westpa/core/binning/_assign.pyx
westpa/core/binning/assign.py
westpa/core/binning/binless.py
westpa/core/binning/binless_driver.py
westpa/core/binning/binless_manager.py
westpa/core/binning/bins.py
westpa/core/binning/mab.py
westpa/core/binning/mab_driver.py
westpa/core/binning/mab_manager.py
westpa/core/kinetics/__init__.py
westpa/core/kinetics/_kinetics.c
westpa-2022.13.dist-info/METADATA
westpa-2022.13.dist-info/WHEEL
westpa-2022.13.dist-info/entry_points.txt
westpa-2022.13.dist-info/top_level.txt
westpa-2022.13.dist-info/RECORD
westpa-2022.13.dist-info/licenses/LICENSE
