Metadata-Version: 2.4
Name: westpa
Version: 2022.13
Summary: WESTPA is a package for constructing and running stochastic simulations using the "weighted ensemble" approach of Huber and Kim (1996).
License-Expression: MIT
Project-URL: Homepage, https://westpa.github.io
Project-URL: Repository, https://github.com/westpa/westpa
Project-URL: Documentation, https://github.readthedocs.io
Project-URL: Issues, https://github.com/westpa/westpa/issues
Classifier: Development Status :: 5 - Production/Stable
Classifier: Intended Audience :: Developers
Classifier: Intended Audience :: Science/Research
Classifier: Operating System :: POSIX
Classifier: Programming Language :: Python
Classifier: Programming Language :: Python :: 3
Classifier: Programming Language :: Cython
Requires-Python: >=3.10
License-File: LICENSE
Requires-Dist: numpy<3,>=1.25.0
Requires-Dist: scipy>=0.19.1
Requires-Dist: h5py>=2.10
Requires-Dist: mdtraj>=1.9.5
Requires-Dist: pyyaml
Requires-Dist: pyzmq
Requires-Dist: matplotlib
Requires-Dist: blessings
Requires-Dist: ipykernel
Requires-Dist: pandas
Requires-Dist: tqdm
Requires-Dist: tables
Provides-Extra: tests
Requires-Dist: pytest; extra == "tests"
Requires-Dist: pytest-cov; extra == "tests"
Requires-Dist: pytest-rerunfailures; extra == "tests"
Requires-Dist: pytest-timeout; extra == "tests"
Provides-Extra: mpi
Requires-Dist: mpi4py; extra == "mpi"
Provides-Extra: dev
Requires-Dist: westpa[tests]; extra == "dev"
Requires-Dist: pre-commit; extra == "dev"
Dynamic: license-file
